{
  "version": 2,
  "news": [
    {
      "id": "2025-11-08-dev2month",
      "date": "2025-11-08",
      "title": "アプリ開発スタートから2ヶ月になりました!",
      "body": "バレエ辞書としてのコア機能に加えて、メモ機能や学習進捗バーなどを追加しました。\n今後は文章のブラッシュアップと動画コンテンツの拡充を進めていきます。",
      "important": true
    },
    {
      "id": "2025-11-15-new-terms",
      "date": "2025-11-15",
      "title": "ジャンプ系の用語を5つ追加しました",
      "body": "assemblé, jeté など、ジャンプに関する用語と説明文を追加しました。動画も順次追加予定です。",
      "important": false
    },
    {
      "id": "2025-11-23-new-terms",
      "date": "2025-11-23",
      "title": "アップデート情報",
      "body": "今回のアップデートでクイズゲームを追加しました",
      "important": false
    }
  ]
}
